{"id":166,"edition":"<i>ASNP</i> III.2.2 (1972), p. 512-515 (R. Cingottini) = <i>Papiri Letterari Greci</i> no. 7 (R. Cingottini, 1978)","inventory":"<a href=\"http://lhpc.arts.kuleuven.ac.be/collections/sample_coll.php?id=5\">Alexandria, inv. </a>611","ldab":"1421","trismegistos":"<a href=\"http://www.trismegistos.org/tm/detail.php?tm=60300\" target=\"_blank\">60300</a>","pack":"1227","vanhaelst":"—","cribiore":"—","vrs":"—","asw":"h109","gigante":"—","cpp":"0166","provenance":"Egypt, unknown","date":"AD 1 - AD 2","bibliography":"pre-edition by G. Botti, <i>Rivista Egiziana</i> 6 (1894), p. 128; subsequent mentions of the papyrus: G. Botti, <i>Bulletin de l'Institut Egyptien </i>8 (1896), p. 120; S. de Ricci, <i>REG</i> 16 (1903), p. 121; E. Breccia, <i>Alexandrea ad Aegyptum</i>, 1914, p. 163; A. Swiderek, <i>Papyrus grecs</i>, 1964, p. 9.","plates":"<i>ASNP</i> III.2.2 (1972), pl. XXXV; <i>Papiri Letterari Greci</i>, pl. IV.","url":"","greektext":"<p>base edition: ed.pr.<p/><a href=\"http://perswww.kuleuven.ac.be/~u0013314/unicode/CPP0166\">Greek text in Unicode</a><p><table cellspacing=22><tr><FONT size=+1><td align=left><font face=\"@arial unicode ms\"><FONT size=+1><p><br>&nbsp; &nbsp; <br>01 &nbsp; &nbsp; <br>02 &nbsp; &nbsp;Axillews a stanu <br>03&nbsp; &nbsp; h ntos tous barb <br>04 &nbsp; &nbsp; rous ek tou Ilioueis to pedion ek <br>05 &nbsp; &nbsp; esqai o Zeus hqele e<br>06&nbsp; &nbsp; Axillews pros Aga <br>07 &nbsp;&nbsp; memnona opws oi Trwes kata <br>08 &nbsp;&nbsp; antes eis to e en<br>09 &nbsp;&nbsp; ai tois au <br>10 &nbsp;&nbsp; tas <br>  &nbsp;&nbsp;</p></p></font></font></td> <td><b><span class=\"grec\">\t   <br>                &nbsp; &nbsp;                         -&nbsp;-&nbsp;-&nbsp;-&nbsp;-&nbsp;-&nbsp;-             &nbsp;&nbsp;&nbsp;&nbsp;&nbsp;&nbsp;<font size=\"-1\"></font>&nbsp;&nbsp;&nbsp;&nbsp;&nbsp;&nbsp;                          <br> 01                  &nbsp; &nbsp;                        [ &nbsp;&nbsp;?&nbsp;&nbsp;  &nbsp; &nbsp;  ]&nbsp;&nbsp;&#803;&nbsp;&nbsp;&#803;&nbsp;&nbsp;&#803;&nbsp;&nbsp;&#803;&nbsp;&nbsp;&#803;&nbsp;&nbsp;&#803;[ &nbsp; &nbsp;   &nbsp; &nbsp; ]&nbsp;&nbsp;&#803;[            <br> 02                  &nbsp; &nbsp;                           [ &nbsp;&nbsp;?&nbsp;&nbsp; ]&nbsp;&nbsp;&#803;&nbsp;&nbsp;&#803; &#913;&#967;&#953;&#955;&#955;&#949;&#969;&#962; &#945;&nbsp;&nbsp;&#803;[&nbsp;&nbsp;&#803;]&nbsp;&nbsp;&#803;&#963;&#964;&#945;&#957;&#965;&#803;            <br> 03                  &nbsp; &nbsp;                           [ &nbsp;&nbsp;?&nbsp;&nbsp; ]&nbsp;&nbsp;&#803;&nbsp;&nbsp;&#803;&nbsp;&nbsp;&#803;&#951;&nbsp;&nbsp;&#803;[&nbsp;&nbsp;&#803;]&#957;&#803;&#964;&#803;&#959;&#803;&#962;&#803; &#964;&#959;&#965;&#962; &#946;&#945;&#961;&#946;&#945;            <br> 04                  &nbsp; &nbsp;                           [&#961;&#959;&#965;&#962; &#949;]&#954;&#803; &#964;&#959;&#965; &#921;&#955;&#953;&#959;&#965; &#949;&#953;[&#962;] &#964;&#959; &#960;&#949;&#948;&#953;&#959;&#957; &#949;&#954;            <br> 05                  &nbsp; &nbsp;                           [ &nbsp;&nbsp;?&nbsp;&nbsp; ]&#949;&#803;&#963;&#803;&#952;&#803;&#945;&#953; &#959; &#918;&#949;&#965;[&#962;] &#951;&#952;&#949;&#803;&#955;&#803;[&#949; &nbsp;&nbsp;&#803;&nbsp;&nbsp;&#803;&nbsp;&nbsp;&#803;&nbsp;&nbsp;&#803;]&#949;            <br> 06                  &nbsp; &nbsp;                           [ &nbsp;&nbsp;?&nbsp;&nbsp; ]&nbsp;&nbsp;&#803;&nbsp;&nbsp;&#803;&nbsp;&nbsp;&#803;&nbsp;&nbsp;&#803;&nbsp;&nbsp;&#803; [&#913;]&#967;&#803;&#953;&#803;&#955;&#803;&#955;&#803;&#949;&#969;&#962; &#960;&#961;&#959;&#962; &#913;&#947;&#945;            <br> 07                  &nbsp; &nbsp;                        [&#956;&#949;&#956;&#957;]&#959;&#957;&#945; &#959;&#960;&#969;&#962; &#959;&#953;&#803; &#932;&#961;&#969;&#803;&#949;&#962; &#954;&#945;&#964;&#945;            <br> 08                  &nbsp; &nbsp;                        [ &nbsp;&nbsp;?&nbsp;&nbsp; ]&#945;&#803;&#957;&#964;&#949;&#962; &#949;&#953;&#962; &#964;&#959; &nbsp;&nbsp;&#803;&#949;&nbsp;&nbsp;&#803;&nbsp;&nbsp;&#803;&nbsp;&nbsp;&#803;&#949;&#957;&nbsp;&nbsp;&#803;&nbsp;&nbsp;&#803;            <br> 09                  &nbsp; &nbsp;                        [ &nbsp;&nbsp;?&nbsp;&nbsp;  &nbsp; &nbsp;  ]&#945;&#953; &#964;&#959;&#953;&#962; &#945;&#965;[&nbsp;&nbsp;&#803;&nbsp;&nbsp;&#803;]&nbsp;&nbsp;&#803;&nbsp;&nbsp;&#803;&nbsp;&nbsp;&#803;&nbsp;&nbsp;&#803;            <br>10                &nbsp; &nbsp;                        [ &nbsp;&nbsp;?&nbsp;&nbsp;  &nbsp; &nbsp;  ]&#964;&#803;&#945;&#962; &nbsp;&nbsp;&#803;&nbsp;&nbsp;&#803;[            <br>                &nbsp; &nbsp;                          -&nbsp;-&nbsp;-&nbsp;-&nbsp;-&nbsp;-&nbsp;-             &nbsp;&nbsp;&nbsp;&nbsp;&nbsp;&nbsp;<font size=\"-1\"></font>&nbsp;&nbsp;&nbsp;&nbsp;&nbsp;&nbsp;                        <br><br><br></SPAN></b></td></FONT></tr></table></p>","author":"anon.","quotedauthor":"[Homerus,><i>Ilias</i>]","genre":"summary","type":"Homerica, mythology","contents":"prose summary (?) of an episode of the <i>Iliad</i>.","propernames":"Achilleus (2); Ilion; Zeus; Agamemnôn; Trôes [Trojans].","mythological":"Achilleus (2); Ilion; Zeus;Agamemnôn; Trôes [Trojans].","material":"papyrus","bookform":"roll","size":"8.2 x 6.5","script":"along the fibres","frontback":"blank","statepreservation":"10 lines broken off by 4-5 letters at the left-hand side, from a column broken at top and bottom.","numberofcolumns":"01","columnwidth":"08.5 - 09","lettersperline":"22-27 (?)","lectionalsigns":"none.","hand":"medium-sized, informal, round, upright, markedly bilinear, fairly regular, proficiently written, separating all letters, without decorations.","lastupdate":""}