{"id":333,"edition":"<font color=\"#FFCC66\"><i>P. Harris</i> 01, 49 (J. E. Powell, 1936)</font>","inventory":"<a href=\"http://lhpc.arts.kuleuven.ac.be/collections/sample_coll.php?id=43\">Birmingham, Orchard Learning Research Centre (Selly Oak College Library)</a> 183 b","ldab":"5497","trismegistos":"<a href=\"http://www.trismegistos.org/tm/detail.php?tm=64277\" target=\"_blank\">64277</a>","pack":"2475","vanhaelst":"—","cribiore":"---","vrs":"---","asw":"---","gigante":"---","cpp":"0333","provenance":"Egypt, Oxyrhynchus ?","date":"AD 3 - AD 4","bibliography":"","plates":"","url":"","greektext":"<p>base edition: ed. pr.</p><p><a href=\"http://perswww.kuleuven.ac.be/~u0013314/unicode/CPP0333\">Greek text in Unicode</a></p><p><table cellspacing=22><tr><FONT size=+1><td align=left><font face=\"@arial unicode ms\"><FONT size=+1>01 &nbsp; &nbsp; aqnas ekmile <br>02 &nbsp; &nbsp; eis Megara <br>03 &nbsp; &nbsp; Korinqos <br>04 &nbsp; &nbsp; Nemeia ths Ellados <br>05 &nbsp; &nbsp; o agwn de kaleitai Dionusia <br>06 &nbsp; &nbsp; Hrakleia</p></font></font></td> <td><b><span class=\"grec\">\t <br> 01                  &nbsp; &nbsp;                        &#945;&#803;&#952;&#957;&#945;&#962; &#949;&#803;&#954;&#803;&#956;&#803;&#953;&#803;&#955;&#803;&#949;&#803;            <br> 02                  &nbsp; &nbsp;                        &#949;&#7984;&#962; &#924;&#8051;&#947;&#945;&#961;&#945;            <br> 03                  &nbsp; &nbsp;                        &#922;&#8057;&#961;&#953;&#957;&#952;&#959;&#962;            <br> 04                  &nbsp; &nbsp;                        <A STYLE=\"text-decoration: none\" HREF=\"#1\"><FONT color=\"#ff943d\">&#925;&#8051;&#956;&#949;&#953;&#945;<SUP>1</SUP></FONT></A>             &nbsp;<font size=\"-1\">m2</font>&nbsp;             &#964;&#8134;&#962; <A STYLE=\"text-decoration: none\" HREF=\"#2\"><FONT color=\"#ff943d\">&#7961;&#955;&#955;&#8049;&#948;&#959;&#962;<SUP>2</SUP></FONT></A>.            <br> 05                  &nbsp; &nbsp;                                    &nbsp;<font size=\"-1\">m1</font>&nbsp;                        &#8001; &#7936;&#947;&#8060;&#957; &#948;&#8050; <A STYLE=\"text-decoration: none\" HREF=\"#3\"><FONT color=\"#ff943d\">[&#954;]&#945;&#955;&#949;&#8150;&#964;&#945;&#953;<SUP>3</SUP></FONT></A> &#916;&#953;&#959;&#957;&#8059;&#963;&#953;&#945;             <br> 06                  &nbsp; &nbsp;                         &nbsp; &nbsp;  &#7977;&#961;&#8049;&#954;&#955;&#949;&#953;&#945;            <br><br><br><A NAME=\"1\"> 04                                  n.               01&nbsp; &nbsp;</A>&#925;&#8051;&#956;&#949;&#953;&#945;              : &#957;&#949;&#956;&#953;&#945; P<br><A NAME=\"2\"> 04                                  n.               02&nbsp; &nbsp;</A>&#7961;&#955;&#955;&#8049;&#948;&#959;&#962; corr m1              : &#949;&#955;&#955;&#949;&#948;&#959;&#962;   <br><A NAME=\"3\"> 05                                  n.               03&nbsp; &nbsp;</A>[&#954;]&#945;&#955;&#949;&#8150;&#964;&#945;&#953;              : [&nbsp;&nbsp;&#803;]&#945;&#955;&#953;&#964;&#945;&#953; P<br></SPAN></b></td></FONT></tr></table></p>","author":"","quotedauthor":"","genre":"list of festivals","type":"cult-related text","contents":"list of Greek cities, and festivals.","propernames":"Megara; Korinthos; Nemeia;  Hellas; Dionysia; Hêrakleia.","mythological":"---","material":"papyrus","bookform":"sheet","size":"8.5 x 5.6","script":"across the fibres","frontback":"document: accounts","statepreservation":"one papyrus fragment (8.5 x 5.6 cm), preserving 6 lines of writing in a single column. ","numberofcolumns":"01","columnwidth":"","lettersperline":"05-22","lectionalsigns":"Marginal note by second hand, within it the first hand has apparently corrected a letter by writing the right one above the line, without, however, erasing the wrong character. Itacistic misspellings: <span class=\"grec\">?</span> for <span class=\"grec\">??</span>.","hand":"","lastupdate":"2003/10/28 Alberto Nodar"}