{"id":34,"edition":"(A) <i>P.Lond.Lit.</i> 142 (H.J.M. Milne, 1927) + (B) <font color=\"#FFCC66\"><i>P.Oxy.</i> 56, 3830 (M.A. Harder, 1989)</font>","inventory":"<a href=\"http://lhpc.arts.kuleuven.ac.be/collections/sample_coll.php?id=192\">London, British Library</a> 1605 C (A) + <a href=\"http://lhpc.arts.kuleuven.ac.be/collections/sample_coll.php?id=264\">Oxford, Sackler Library, Papyrology Rooms</a>(B) ","ldab":"2757","trismegistos":"<a href=\"http://www.trismegistos.org/tm/detail.php?tm=61608\" target=\"_blank\">61608</a>","pack":"1188 (A) = M-P 1185.03 (A+B)","vanhaelst":"—","cribiore":"—","vrs":"<font color=\"#FFCC66\">50</font>","asw":"h069 + h115","gigante":"—","cpp":"0034","provenance":"Egypt, Oxyrhynchus","date":"AD 2","bibliography":"H. Erbse, pap. VII (vol. II, p. 392-393, but see also corrigenda, vol. VII, p. 266); A. Körte, <i>APF</i> 10 (1932), p. 235; R. Pfeiffer, <i>Philologus</i> 92 (1937), p. 16-18 [= <i>Ausgewählte Schriften</i>, 1960, p. 39-41]; M. Haslam, <i>BASP</i> 27 (1990), p. 31-36; idem, <i>Glotta</i> 70 (1992), p. 35-38; W. Luppe, <i>Gnomon</i> 64 (1992), p. 291-293; idem, <i>APF</i> 39 (1993), p. 9-11; cf. also F. Montanari, in: <i>Greek Lit. Theory after Aristotle</i>, Amsterdam, 1995, p. 135-172; <font color=\"#FFCC66\">Pherecydes fr. 158b Fowler</font>= fr. 33 Dolcetti.","plates":"(A) Erbse, vol. II; (B) ed. princ. pl. II.","url":"http://www.csad.ox.ac.uk/POxy/papyri/vol56/pages/3830.htm","greektext":" <p> base edition: <i>Greek Reader's digests? </i>, Leiden, 1998 (M.R. van Rossum-Steenbeek) <br> other editions: ed.pr.<br> <i>APF</i> 39 (1993), p. 9-11 (W.Luppe) <br> <i> Early Greek Mythography </i> , Oxford, 2000 (R.L. Fowler) </p>  <a href=\"http://perswww.kuleuven.ac.be/~u0013314/unicode/CPP0034\">Greek text in Unicode</a><p><table cellspacing=22><tr><FONT size=+1><td align=left><font face=\"@arial unicode ms\"><FONT size=+1><p>Fr. 1+ fr. 2 col. I <br>01 &nbsp; &nbsp; panteuxian h d <br>02 &nbsp; &nbsp; twn d Elenos Priamoio filos pais sunqeto qumwimuqeuetai <br>03 &nbsp; &nbsp; twn ec Ekabhs genomenwn Priamwi paidwn <br>04 &nbsp; &nbsp; ton Elenon kai thn Kassandran didumous gegenhsqai <br>05 &nbsp; &nbsp; twn de geneqliwn uper autwn sunteloumenwn <br>06 &nbsp; &nbsp; en twi tou Qumbraiou Apollwnos ierwi <br>07 &nbsp; &nbsp; ton Elenon kai thn Kassandran e <br>08 &nbsp; &nbsp; thi de usteraiai elqontas <br>09 &nbsp; &nbsp; ai tais glwssais <br>10 &nbsp; &nbsp; perikaqairontas <br>11 &nbsp; &nbsp; de ofeis euqews <br>12 &nbsp; &nbsp; hsan oqen sunebh <br>13 &nbsp; &nbsp; tous paidas ths mantikhs metasxein Antikleidhs <br>14 &nbsp; &nbsp; shma te oi xeuwsin epi platei Ellhspontwi Aqamas <br>15 &nbsp; &nbsp; o Aiolou men pais basileuwn de twn Qhbwn ghmas <br>16 &nbsp; &nbsp; Inw thn Kadmou qugatera esxe paidas duo Learxon <br>17 &nbsp; &nbsp; kai Melikerthn kata de Hras prostagmata <br>18 &nbsp; &nbsp; apopemyamenos epeghme Nefelhn <br>19 &nbsp; &nbsp; ec hs esxe duo paidas Ellhn te kai Fricon mignumenon <br>20 &nbsp; &nbsp; de auton laqra thi Inoi katopteusasa h Nefelh <br>21 &nbsp; &nbsp; wixeto palin de ths oikias epikrathsasa h Inw epe</p><p> Fr. 2 col. II = fr. 3 col. I <br>22 &nbsp; &nbsp; <br>23 &nbsp; &nbsp; q <br>24 &nbsp; &nbsp; ta <br>25 &nbsp; &nbsp; <br>26 &nbsp; &nbsp; t <br>27 &nbsp; &nbsp; gaihs kai pontoio in Iapetos te Kronos te </p><p> fr. 3 <br>28 &nbsp; &nbsp; Ouranou kai Ghs paid <br>29 &nbsp; &nbsp; hi oti te neos wn <br>30 &nbsp; &nbsp; n o de Zeus m <br>31 &nbsp; &nbsp; balwn a <br>32 &nbsp; &nbsp; keraunois gar kai astrapais <br>33 &nbsp; &nbsp; s eneircen tee <br>34 &nbsp; &nbsp; arxhn Kronwi <br>35 &nbsp; &nbsp; t diaferein ofei <br>36 &nbsp; &nbsp; thn ap autou proshgoreu h d istoria <br>37 &nbsp; &nbsp; par Euforiwni <br>38 &nbsp; &nbsp; oion ote prwton lipon Ellada kalligunaika Foinic <br>39 &nbsp; &nbsp; o Amuntoros kai Ippodameias <br>40 &nbsp; &nbsp; peisqeis upo ths mhtros <br>41 &nbsp; &nbsp; opws mishi touton e eparatai <br>42 &nbsp; &nbsp; kata tou Foinikos mh pote paidas <br>43 &nbsp; &nbsp; gennhsasqai <br>44 &nbsp; &nbsp; axqos paraginetai o de auton <br>45 &nbsp; &nbsp; asmenws edexeto <br>46 &nbsp; &nbsp; ankatiqetai tou pa <br>47 &nbsp; &nbsp; k an tose <br>48 &nbsp; &nbsp; pare ei </p><p> col. I <br>35 &nbsp; &nbsp; <br>36 &nbsp; &nbsp; s <br>37 &nbsp; &nbsp; thn <br>38 &nbsp; &nbsp; un <br>39 &nbsp; &nbsp; <br>40 &nbsp; &nbsp; <br>41 &nbsp; &nbsp; <br>42 &nbsp; &nbsp; <br>43 &nbsp; &nbsp; <br>44 &nbsp; &nbsp; <br>45 &nbsp; &nbsp; <br>46 &nbsp; &nbsp; ti <br>47 &nbsp; &nbsp; <br>48 &nbsp; &nbsp; </p></p></font></font></td> <td><b><span class=\"grec\"><br>Fr. 1+ fr. 2 col. I            <br> 01                  &nbsp; &nbsp;                         &nbsp; &nbsp;  &nbsp; &nbsp;  &nbsp; &nbsp;  &nbsp; &nbsp;   &nbsp; &nbsp;  &nbsp; &nbsp;  &nbsp; &nbsp;  &nbsp; &nbsp;  &#960;&#945;]&#957;&#803;&#964;&#949;&#965;&#967;&#8055;&#945;&#957; &#7969; <a STYLE=\"text-decoration: none\" HREF=\"#1\"><font color=\"#ff943d\">&#948;&#8217;<sup>1</sup></font></a> <a STYLE=\"text-decoration: none\" HREF=\"#2\"><font color=\"#ff943d\">&nbsp;&nbsp;&#803;[<sup>2</sup></font></a>            <br> 02                                         <b>&#964;&#8182;&#957; &#948;&#8217; &#8158; &#917;&#955;&#949;&#957;&#959;&#962; &#928;&#961;&#953;&#8049;&#956;&#959;&#953;&#959; &#966;&#8055;&#955;&#959;&#962; &#960;]&#945;&#803;&#8150;&#962; &#963;&#8059;&#957;&#952;&#949;&#964;&#959;               &#952;&#965;&#956;&#803;[&#8182;&#953; </b> &#956;&#965;&#8208;            <br> 03                  &nbsp; &nbsp;                        &#952;&#949;&#8059;&#949;&#964;&#945;&#953; &#964;&#8182;&#957; &#7952;&#958; &#701; &#917;&#954;&#8049;&#946;&#951;&#962; &#947;&#949;&#957;&#959;]&#956;&#8051;&#957;&#969;&#957; &#928;&#961;&#953;&#8049;&#956;&#969;&#803;[&#953; &#960;&#945;&#8055;&#948;&#969;&#957;            <br> 04                  &nbsp; &nbsp;                        &#964;&#8056;&#957;  &#8158; &#917;&#955;&#949;&#957;&#959;&#957; &#954;&#945;&#8054; &#964;&#8052;&#957; &#922;&#945;&#963;&#963;&#8049;&#957;&#948;&#961;]&#945;&#803;&#957; &#948;&#953;&#948;&#8059;&#956;&#959;&#965;&#962; &#947;&#803;[&#949;&#947;&#949;&#957;&#8134;&#8208;            <br> 05                  &nbsp; &nbsp;                        &#963;&#952;&#945;&#953;&#903; &#964;&#8182;&#957; &#948;&#8050; &#947;&#949;&#957;&#949;&#952;&#955;&#8055;&#969;&#957; &#8017;&#960;&#8050;&#961;] &#945;&#8016;&#964;&#8182;&#803;&#957;&#803; &#963;&#965;&#957;&#964;&#949;[&#955;&#959;&#965;&#956;&#8051;&#8208;            <br> 06                  &nbsp; &nbsp;                        &#957;&#969;&#957; &#7952;&#957; &#964;&#8182;&#953; &#964;&#959;&#8166; &#920;&#965;&#956;&#946;&#961;&#945;&#8055;&#959;&#965; &#700; &#913;&#960;&#8057;]&#955;&#955;&#969;&#957;&#959;&#962; <a STYLE=\"text-decoration: none\" HREF=\"#3\"><font color=\"#ff943d\">&#7985;&#949;&#961;&#8182;[&#953;<sup>3</sup></font></a>            <br> 07                  &nbsp; &nbsp;                         &nbsp; &nbsp;  &nbsp; &nbsp;  <a STYLE=\"text-decoration: none\" HREF=\"#4\"><font color=\"#ff943d\">&#964;&#8056;&#957;<sup>4</sup></font></a>  &#8158; &#917;&#955;&#949;&#957;&#959;&#957;            &#954;&#945;&#8054; &#964;&#8052;&#957; &#922;]&#945;&#963;&#963;&#8049;&#957;&#948;&#961;&#945;&#957; <a STYLE=\"text-decoration: none\" HREF=\"#5\"><font color=\"#ff943d\">&#949;[<sup>5</sup></font></a>              <br> 08                  &nbsp; &nbsp;                         &nbsp; &nbsp;  &nbsp; &nbsp;  &nbsp; &nbsp; <a STYLE=\"text-decoration: none\" HREF=\"#6\"><font color=\"#ff943d\">&#964;&#8134;&#953;<sup>6</sup></font></a>  &#948;&#8050;            &#8017;&#963;]&#964;&#803;&#949;&#961;&#945;&#8055;&#945;&#953; &#7952;&#955;&#952;&#8057;&#957;&#964;&#945;&#962; <a STYLE=\"text-decoration: none\" HREF=\"#7\"><font color=\"#ff943d\">&nbsp;&nbsp;&#803;[<sup>7</sup></font></a>              <br> 09                  &nbsp; &nbsp;                         &nbsp; &nbsp;  &nbsp; &nbsp;  &nbsp; &nbsp;  &nbsp; &nbsp;   &nbsp; &nbsp;  &nbsp; &nbsp;  &nbsp; &nbsp;  &nbsp; &nbsp;  &nbsp; &nbsp;  <a STYLE=\"text-decoration: none\" HREF=\"#8\"><font color=\"#ff943d\">]&nbsp;&nbsp;&#803;&nbsp;&nbsp;&#803;&nbsp;&nbsp;&#803;&#945;&#953;<sup>8</sup></font></a>  &#964;&#945;&#8150;&#962;  <a STYLE=\"text-decoration: none\" HREF=\"#9\"><font color=\"#ff943d\">&#947;[&#955;&#8061;&#963;&#8208;<sup>9</sup></font></a>            <br>10                &nbsp; &nbsp;                        <a STYLE=\"text-decoration: none\" HREF=\"#10\"><font color=\"#ff943d\">&#963;&#945;&#953;&#962;<sup>10</sup></font></a>  &nbsp; &nbsp;  &nbsp; &nbsp;  &nbsp; &nbsp;  &nbsp; &nbsp;   <a STYLE=\"text-decoration: none\" HREF=\"#11\"><font color=\"#ff943d\">]&nbsp;&nbsp;&#803;<sup>11</sup></font></a> &#960;&#949;&#961;&#953;&#954;&#945;&#952;&#945;&#8055;&#961;&#959;&#957;&#964;&#945;&#803;[&#962;             <br>11                &nbsp; &nbsp;                         &nbsp; &nbsp;  &nbsp; &nbsp;  &nbsp; &nbsp;  &nbsp; &nbsp;   &nbsp; &nbsp;  <a STYLE=\"text-decoration: none\" HREF=\"#12\"><font color=\"#ff943d\">]&#948;&#8050;<sup>12</sup></font></a> &#8004;&#966;&#949;&#953;&#962; <a STYLE=\"text-decoration: none\" HREF=\"#13\"><font color=\"#ff943d\">&#949;&#8016;&#952;&#8051;&#969;[&#962; <sup>13</sup></font></a>            <br>12                &nbsp; &nbsp;                         &nbsp; &nbsp;  &nbsp; &nbsp;  &nbsp; &nbsp;  &nbsp; &nbsp;   &nbsp; &nbsp;  <a STYLE=\"text-decoration: none\" HREF=\"#14\"><font color=\"#ff943d\">]&nbsp;&nbsp;&#803;&#951;&#963;&#945;&#957;<sup>14</sup></font></a> &#8005;&#952;&#949;&#957; &#963;&#965;&#803;[&#957;&#8051;&#946;&#951;            <br>13                &nbsp; &nbsp;                         &#964;&#959;&#8058;&#962; &#960;&#945;&#8150;&#948;&#945;&#962; &#964;&#8134;&#962; &#956;&#945;&#957;&#964;&#953;&#954;&#8134;&#962;] &#956;&#949;&#964;&#945;&#963;&#967;&#949;&#8150;&#957; <a STYLE=\"text-decoration: none\" HREF=\"#15\"><font color=\"#ff943d\">[&nbsp;&nbsp;&#803;&nbsp;&nbsp;&#803;&nbsp;&nbsp;&#803;]&nbsp;&nbsp;&#803;&#773;<sup>15</sup></font></a> <a STYLE=\"text-decoration: none\" HREF=\"#16\"><font color=\"#ff943d\">&#700;                  &#913;&#957;&#964;&#953;&#954;&#955;&#949;&#8055;&#948;(&#951;&#962;)<sup>16</sup></font></a>            <br>14                                       <b>&#963;&#8134;&#956;&#8049; &#964;&#949; &#959;&#7985; &#967;&#949;&#8059;&#969;&#963;&#953;&#957; &#7952;&#960;&#8054; &#960;&#955;&#945;&#964;]&#949;&#8150; &#701;               &#917;&#955;&#955;&#951;&#963;&#960;[&#8057;&#957;&#964;]&#969;&#803;&#953;&#803;</b>  &nbsp; &nbsp; &#700; &#913;&#952;&#8049;&#8208;            <br>15                &nbsp; &nbsp;                        &#956;&#945;&#962; &#8001; &#913;&#7984;&#8057;&#955;&#959;&#965; &#956;&#8050;&#957; &#960;&#945;&#8150;&#962; <a STYLE=\"text-decoration: none\" HREF=\"#17\"><font color=\"#ff943d\">&#946;&#945;&#963;&#953;&#955;&#949;&#8059;]&#969;&#957;<sup>17</sup></font></a> &#948;&#8050; &#964;&#8182;&#957; &#920;&#951;&#946;&#8182;&#957; &#947;&#8053;&#8208;            <br>16                &nbsp; &nbsp;                        &#956;&#945;&#962; &#700; &#921;&#957;&#8060; &#964;&#8052;&#957; &#922;&#8049;&#948;&#956;&#959;&#965; &#952;&#965;&#947;&#945;&#964;&#8051;&#961;]&#945; &#7956;&#963;&#967;&#949; &#960;&#945;&#8150;&#948;&#945;&#962; &#948;&#8059;&#959; &#923;&#8051;&#8208;            <br>17                &nbsp; &nbsp;                        &#945;&#961;&#967;&#959;&#957; &#954;&#945;&#8054; &#924;&#949;&#955;&#953;&#954;&#8051;&#961;&#964;&#951;&#957;&#903; &#954;&#945;&#964;&#8048; &#948;]&#8050; &#8158; &#919;&#961;&#945;&#962; &#960;&#961;&#959;&#963;&#964;&#8049;&#947;&#956;&#945;&#964;&#945;             <br>18                &nbsp; &nbsp;                        &#7936;&#960;&#959;&#960;&#949;&#956;&#968;&#8049;&#956;&#949;&#957;&#959;&#962;  &nbsp; &nbsp;  &nbsp; &nbsp;  &nbsp; &nbsp; ] &#7952;&#960;&#8051;&#947;&#951;&#956;&#949; <a STYLE=\"text-decoration: none\" HREF=\"#18\"><font color=\"#ff943d\">&#925;&#949;&#966;&#8051;&#955;&#951;&#957;<sup>18</sup></font></a>             <br>19                &nbsp; &nbsp;                        &#7952;&#958; &#7975;&#962; &#7956;&#963;&#967;&#949; &#948;&#8059;&#959; &#960;&#945;&#8150;&#948;&#945;&#962; &#701; &#917;&#955;&#955;&#951;&#957; &#964;]&#949;&#803; &#954;&#945;&#8054; <a STYLE=\"text-decoration: none\" HREF=\"#19\"><font color=\"#ff943d\">&#934;&#961;&#8055;&#958;&#959;&#957;&#903;<sup>19</sup></font></a> &#956;&#953;&#947;&#957;&#8059;&#956;&#949;&#8208;            <br>20                &nbsp; &nbsp;                        &#957;&#959;&#957; &#948;&#8050; &#945;&#8016;&#964;&#8056;&#957; &#955;&#8049;&#952;&#961;&#945; &#964;&#8134;&#953; &#700; &#921;&#957;&#959;&#8150; &#954;&#945;&#964;]&#959;&#960;&#964;&#949;&#8059;&#963;&#945;&#963;&#945; &#7969; &#925;&#949;&#966;&#8051;&#8208;            <br>21                &nbsp; &nbsp;                        &#955;&#951; &#8036;&#953;&#967;&#949;&#964;&#959;, &#960;&#8049;&#955;&#953;&#957; &#948;&#8050; &#964;&#8134;&#962; &#959;&#7984;&#954;&#8055;&#945;&#962; &#7952;&#960;&#953;&#954;]&#961;&#945;&#964;&#8053;&#963;&#945;&#963;&#945; &#7969; <a STYLE=\"text-decoration: none\" HREF=\"#20\"><font color=\"#ff943d\">&#700; &#921;&#957;&#803;&#8060;&#803;<sup>20</sup></font></a> <a STYLE=\"text-decoration: none\" HREF=\"#21\"><font color=\"#ff943d\">&#7952;&#960;&#949;&#8208;<sup>21</sup></font></a>             <br>                &nbsp; &nbsp;                         -&nbsp;-&nbsp;-&nbsp;-&nbsp;-&nbsp;-&nbsp;-             &nbsp;&nbsp;&nbsp;&nbsp;&nbsp;&nbsp;<font size=\"-1\"></font>&nbsp;&nbsp;&nbsp;&nbsp;&nbsp;&nbsp;                        <br>Fr. 2 col. II + fr. 3 col. I            <br>22                &nbsp; &nbsp;                        &nbsp;&nbsp;&#803;[            <br>23                &nbsp; &nbsp;                        &nbsp;&nbsp;&#803;&#952;&nbsp;&nbsp;&#803;[            <br>24                &nbsp; &nbsp;                        &#964;<a STYLE=\"text-decoration: none\" HREF=\"#22\"><font color=\"#ff943d\">&#945;&#803;&nbsp;&nbsp;&#803;[<sup>22</sup></font></a>            <br>25                &nbsp; &nbsp;                        &nbsp;&nbsp;&#803;&nbsp;&nbsp;&#803;&nbsp;&nbsp;&#803;[            <br>26                &nbsp; &nbsp;                        <a STYLE=\"text-decoration: none\" HREF=\"#23\"><font color=\"#ff943d\">&#964;&#803;&nbsp;&nbsp;&#803;&nbsp;&nbsp;&#803;[<sup>23</sup></font></a>            <br>27                                        <b>&#947;&#945;&#8055;&#951;&#962; [&#954;&#945;&#8054; &#960;&#8057;&#957;&#964;&#959;&#953;&#959;, &#7989;&#957;&#8217; &#700; &#921;&#8049;&#960;&#949;&#964;&#8057;&#962; &#964;&#949; &#922;&#961;&#8057;&#957;&#959;&#962;               &#964;&#949;</b>             <br>                &nbsp; &nbsp;                        lines lost             <br>Fr. 3            <br>                &nbsp; &nbsp;                         -&nbsp;-&nbsp;-&nbsp;-&nbsp;-&nbsp;-&nbsp;-             &nbsp;&nbsp;&nbsp;&nbsp;&nbsp;&nbsp;<font size=\"-1\"></font>&nbsp;&nbsp;&nbsp;&nbsp;&nbsp;&nbsp;             &#927;&#8016;&#8208;            <br>28                &nbsp; &nbsp;                        &#961;]&#945;&#957;&#959;&#8166; &#954;&#945;&#8054; &#915;&#8134;&#962; &#960;&#945;[&#953;&#948;&#8208;            <br>29                &nbsp; &nbsp;                        &nbsp;&nbsp;&#803;]&#951;&#953; &#8005;&#964;&#953; &#964;&#949; &#957;&#8051;&#959;&#962; &#8036;]&#957;            <br>30                &nbsp; &nbsp;                        &nbsp;&nbsp;&#803;&nbsp;&nbsp;&#803;]<a STYLE=\"text-decoration: none\" HREF=\"#24\"><font color=\"#ff943d\">&#957;&#903;<sup>24</sup></font></a> &#8001; &#948;&#8050; &#918;&#949;&#8058;&#962; &#956;[            <br>31                &nbsp; &nbsp;                        &nbsp;&nbsp;&#803;&nbsp;&nbsp;&#803;]&nbsp;&nbsp;&#803; &#946;&#945;&#955;&#8060;&#957; &#945;&nbsp;&nbsp;&#803;[            <br>32                &nbsp; &nbsp;                        &#954;&#949;&#961;]&#945;&#965;&#957;&#959;&#8150;&#962; &#947;&#8048;&#961; &#954;&#945;&#8054; &#7936;&#803;[&#963;&#964;&#961;&#945;&#960;&#945;&#8150;&#962;             <br>33                &nbsp; &nbsp;                        ]&#962; &#7952;&#957;&#949;&#8150;&#961;&#958;&#949;&#957; &#964;&#949;&#949;&#803;[            <br>34                &nbsp; &nbsp;                        ]&#7936;&#961;&#967;&#8052;&#957; &#922;&#961;&#8057;&#957;&#969;&#953;&nbsp;&nbsp;&#803;[            <br>35                &nbsp; &nbsp;                        &#964;&nbsp;&nbsp;&#803;&nbsp;&nbsp;&#803;&#948;&#803;&#953;&#803;&#945;&#966;&#8051;&#961;&#949;&#953;&#957; &#959;&#966;&#949;&#953;[            <br>36                &nbsp; &nbsp;                        &#964;&#951;&#957; &#7936;[&#960;&#8217;] &#945;&#8016;&#964;&#959;&#8166; &#960;&#961;&#959;&#963;&#951;[&#947;&#959;&#961;&#949;&#965; &nbsp; &nbsp;  &nbsp; &nbsp;  &nbsp; &nbsp; &#7969; <a STYLE=\"text-decoration: none\" HREF=\"#25\"><font color=\"#ff943d\">(&#948;&#8217;)<sup>25</sup></font></a> &#7985;&#8208;             <br>37                &nbsp; &nbsp;                        &#963;&#964;&#959;&#961;&#8055;&#945; &#960;&#945;&#961;&#8217; &#917;&#803;&#8016;&#966;&#959;&#961;&#803;&#8055;&#803;&#969;&#803;&#957;&#803;&#953;&#803;[            <br>38                                        <b>&#959;&#7991;&#959;&#957; &#8005;&#964;&#949; </b> <a STYLE=\"text-decoration: none\" HREF=\"#26\"><font color=\"#ff943d\">[&#960;&#961;]&#8182;&#964;&#959;&#957; <sup>26</sup></font></a><b> &#955;&#8055;&#960;&#959;&#957; [&#701; &#917;&#955;&#955;&#8049;&#948;&#945; &#954;&#945;&#955;&#955;&#953;&#947;&#8059;&#957;&#945;&#953;&#954;&#945; &#934;&#959;&#8150;&#957;&#953;&#958;</b>             <br>39                &nbsp; &nbsp;                        &#8001;&#803; &#700; &#913;&#956;&#8059;&#803;&#957;&#803;&#964;&#959;&#961;&#959;&#962; &#954;&#945;&#8054; &#701; &#921;&#960;&#960;&#959;&#803;[&#948;&#945;&#956;&#949;&#8055;&#945;&#962;             <br>40                &nbsp; &nbsp;                        &#960;&#949;&#953;&#963;&#952;&#949;&#8054;&#962; &#8017;&#960;&#8056; &#964;&#8134;&#962; &#956;[&#951;&#964;&#961;&#8056;&#962;             <br>41                &nbsp; &nbsp;                        &#8005;]&#960;&#969;&#962; &#956;&#953;&#963;&#8134;&#953; &#964;&#959;&#8166;&#964;&#959;&#957; &#949;&#803;[ &nbsp; &nbsp;  &nbsp; &nbsp;  &nbsp; &nbsp; &#7952;&#960;&#945;&#961;&#8118;&#8208;            <br>42                &nbsp; &nbsp;                        &#964;&#803;&#945;&#803;[&#953;] &#954;&#945;&#964;&#8048; &#964;&#959;&#8166; &#934;&#959;&#8055;&#957;&#953;&#954;[&#959;&#962; &nbsp; &nbsp;  &nbsp; &nbsp;  &nbsp; &nbsp; &#956;&#8053; &#960;&#959;&#964;&#949; &#960;&#945;&#8150;&#8208;            <br>43                &nbsp; &nbsp;                         &#948;&#803;&#945;&#803;&#962; <a STYLE=\"text-decoration: none\" HREF=\"#27\"><font color=\"#ff943d\">&#947;&#949;&#957;&#957;&#8053;&#963;&#945;&#963;&#952;&#945;&#953;&#903;<sup>27</sup></font></a> &nbsp;&nbsp;&#803;[            <br>44                &nbsp; &nbsp;                        &#7940;&#967;&#803;&#952;&#959;&#962; &#960;&#945;&#961;&#945;&#947;&#8055;&#957;&#949;&#964;&#945;&#803;[&#953; &nbsp; &nbsp;  &nbsp; &nbsp;  &nbsp; &nbsp; &#8001; &#948;&#8050; &#945;&#8016;&#8208;            <br>45                &nbsp; &nbsp;                        &#964;&#8056;&#957; &#7936;&#963;&#956;&#8051;&#957;&#969;&#962; &#7952;&#948;&#8051;&#967;[&#949;&#964;&#959;            <br>46                &nbsp; &nbsp;                        &#945;&#957;&#954;&#945;&#803;&#964;&#953;&#952;&#949;&#964;&#945;&#953; &#964;&#959;&#8166; &#960;&#945;[            <br>47                &nbsp; &nbsp;                        &#954;&nbsp;&nbsp;&#803;&#945;&#957;[&nbsp;&nbsp;&#803;&nbsp;&nbsp;&#803;&nbsp;&nbsp;&#803;&nbsp;&nbsp;&#803;&nbsp;&nbsp;&#803;&nbsp;&nbsp;&#803;&nbsp;&nbsp;&#803;]&nbsp;&nbsp;&#803;&#964;&#959;&#963;&#949;&nbsp;&nbsp;&#803;[            <br>48                &nbsp; &nbsp;                        &#960;&#945;&#961;&#949;&nbsp;&nbsp;&#803;[&nbsp;&nbsp;&#803;&nbsp;&nbsp;&#803;&nbsp;&nbsp;&#803;&nbsp;&nbsp;&#803;&nbsp;&nbsp;&#803;&nbsp;&nbsp;&#803;]&nbsp;&nbsp;&#803;&#949;&#953;[            <br>Col. I            <br>                &nbsp; &nbsp;                         -&nbsp;-&nbsp;-&nbsp;-&nbsp;-&nbsp;-&nbsp;-             &nbsp;&nbsp;&nbsp;&nbsp;&nbsp;&nbsp;<font size=\"-1\"></font>&nbsp;&nbsp;&nbsp;&nbsp;&nbsp;&nbsp;                         <br>35                &nbsp; &nbsp;                        ]&nbsp;&nbsp;&#803;&nbsp;&nbsp;&#803;[            <br>36                &nbsp; &nbsp;                        ]&nbsp;&nbsp;&#803;&#962;             <br>37                &nbsp; &nbsp;                        ]&nbsp;&nbsp;&#803;&#964;&#951;&#957;            <br>38                &nbsp; &nbsp;                        ]&nbsp;&nbsp;&#803;&#965;&#803;&#957;&#803;            <br>39                &nbsp; &nbsp;                                    <br>40                &nbsp; &nbsp;                                    <br>41                &nbsp; &nbsp;                                    <br>42                &nbsp; &nbsp;                                    <br>43                &nbsp; &nbsp;                                     <br>44                &nbsp; &nbsp;                                    <br>45                &nbsp; &nbsp;                                    <br>46                &nbsp; &nbsp;                        ]&#964;&#953;            <br>47                &nbsp; &nbsp;                                    <br>48                &nbsp; &nbsp;                                    <br><br><br><a NAME=\"1\"> 01                                  n.               01&nbsp; &nbsp;</a>&#948;&#8217; VRS             : &#948;&#8217; P<br><a NAME=\"2\"> 01                                  n.               02&nbsp; &nbsp;</a>&nbsp;&nbsp;&#803;[ VRS             : &#7985;&#803;[&#963;&#964;&#959;&#961;&#8055;&#945; &#960;(&#945;&#961;&#8048;) &#934;&#949;&#961;&#949;&#954;&#8059;(&#948;&#949;&#953;) suppl Fowler  <br><a NAME=\"3\"> 06                                  n.               03&nbsp; &nbsp;</a>&#7985;&#949;&#961;&#8182;[&#953; VRS             : &#7985;&#949;&#961;&#8182;[&#953; &#964;&#959;&#8058;&#962; suppl Luppe  <br><a NAME=\"4\"> 07                                  n.               04&nbsp; &nbsp;</a>&#964;&#8056;&#957; VRS             : &#964;&#959;&#954;&#8051;&#945;&#962; &#964;&#8056;&#957; suppl Luppe  <br><a NAME=\"5\"> 07                                  n.               05&nbsp; &nbsp;</a>&#949;[ VRS             : &#7952;[&#957; &#964;&#8182;&#953; &#957;&#945;&#8208; suppl Luppe  <br><a NAME=\"6\"> 08                                  n.               06&nbsp; &nbsp;</a>&#964;&#8134;&#953; VRS             : &#8182;&#953; &#954;&#945;&#964;&#945;&#955;&#953;&#960;&#949;&#8150;&#957;. &#964;&#8134;&#953; suppl Luppe  <br><a NAME=\"7\"> 08                                  n.               07&nbsp; &nbsp;</a>&nbsp;&nbsp;&#803;[ VRS             : &#949;&#803;[&#8017;&#961;&#949;&#8150;&#957; suppl Luppe  <br><a NAME=\"8\"> 09                                  n.               08&nbsp; &nbsp;</a>]&nbsp;&nbsp;&#803;&nbsp;&nbsp;&#803;&nbsp;&nbsp;&#803;&#945;&#953; VRS             : &#948;&#8059;&#959; &#8004;&#966;&#949;&#953;&#962; &#963;&#965;&#956;&#960;&#945;&#961;&#8057;&#957;&#964;&#945;&#962; &#964;&#959;&#8150;&#962; &#960;&#945;&#953;&#963;&#8054;]&#957;&#803;            &#954;&#803;&#945;&#8054; suppl Luppe  <br><a NAME=\"9\"> 09                                  n.               09&nbsp; &nbsp;</a>&#947;[&#955;&#8061;&#963;&#8208; VRS             : &#947;&#803;[&#955;&#8061;&#964;&#8208; Luppe  <br><a NAME=\"10\">10                                n.               10&nbsp; &nbsp;</a>&#963;&#945;&#953;&#962; VRS             : &#964;&#945;&#953;&#962; Luppe  <br><a NAME=\"11\">10                                n.               11&nbsp; &nbsp;</a>]&nbsp;&nbsp;&#803; VRS             : &#964;&#945;&#953;&#962; &#964;&#8048; &#964;&#959;&#8059;&#964;&#969;&#957;            &#945;&#7984;&#963;&#952;&#951;&#964;&#8053;&#961;&#953;]&#945;&#803; suppl Luppe  <br><a NAME=\"12\">11                                n.               12&nbsp; &nbsp;</a>]&#948;&#8050; VRS             : &#959;&#7985;] &#948;&#8050; suppl Luppe  <br><a NAME=\"13\">11                                n.               13&nbsp; &nbsp;</a>&#949;&#8016;&#952;&#8051;&#969;[&#962;  VRS             : &#949;&#8016;&#952;&#8051;&#969;[&#962; &#949;&#7984;&#962; suppl Luppe  <br><a NAME=\"14\">12                                n.               14&nbsp; &nbsp;</a>]&nbsp;&nbsp;&#803;&#951;&#963;&#945;&#957; VRS             : &#964;&#8048;&#962; &#954;&#945;&#964;&#945;&#957;&#964;&#953;&#954;&#961;&#8058; &#948;&#8049;&#966;&#957;&#945;&#962;            &#7936;&#960;&#8051;]&#946;&#803;&#951;&#963;&#945;&#957;. suppl Luppe  <br><a NAME=\"15\">13                                n.               15&nbsp; &nbsp;</a>[&nbsp;&nbsp;&#803;&nbsp;&nbsp;&#803;&nbsp;&nbsp;&#803;]&nbsp;&nbsp;&#803;&#773; VRS             : [&#959;&#8021;&#964;]&#969;&#803;&#773;(&#962;) suppl Luppe  <br><a NAME=\"16\">13                                n.               16&nbsp; &nbsp;</a>&#700;            &#913;&#957;&#964;&#953;&#954;&#955;&#949;&#8055;&#948;(&#951;&#962;) VRS             : &#945;&#957;&#964;&#953;&#954;&#955;&#949;&#953;`&#948;&acute; P<br><a NAME=\"17\">15                                n.               17&nbsp; &nbsp;</a>&#946;&#945;&#963;&#953;&#955;&#949;&#8059;]&#969;&#957; suppl VRS             : ]&#969;&#957; ed.pr.  <br><a NAME=\"18\">18                                n.               18&nbsp; &nbsp;</a>&#925;&#949;&#966;&#8051;&#955;&#951;&#957; VRS             : &#957;&#949;&#966;&#949;&#955;&#951;&#957;&#903; P<br><a NAME=\"19\">19                                n.               19&nbsp; &nbsp;</a>&#934;&#961;&#8055;&#958;&#959;&#957;&#903; VRS             : &#966;&#961;&#953;&#958;&#959;&#957;&#903; P<br><a NAME=\"20\">21                                n.               20&nbsp; &nbsp;</a>&#700; &#921;&#957;&#803;&#8060;&#803; VRS             : &#953;&#776;&#957;&#803;&#969;&#803; P<br><a NAME=\"21\">21                                n.               21&nbsp; &nbsp;</a>&#7952;&#960;&#949;&#8208; VRS             : &#7952;&#960;&#949;&#8208;[&#946;&#959;&#8059;&#955;&#949;&#965;&#963;&#949; suppl ed.pr.  <br><a NAME=\"22\">24                                n.               22&nbsp; &nbsp;</a>&#945;&#803;&nbsp;&nbsp;&#803;[ suppl VRS             : &nbsp;&nbsp;&#803;&nbsp;&nbsp;&#803;[ suppl ed.pr.  <br><a NAME=\"23\">26                                n.               23&nbsp; &nbsp;</a>&#964;&#803;&nbsp;&nbsp;&#803;&nbsp;&nbsp;&#803;[ suppl VRS             : &nbsp;&nbsp;&#803;&nbsp;&nbsp;&#803;&nbsp;&nbsp;&#803;[ ed.pr.  <br><a NAME=\"24\">30                                n.               24&nbsp; &nbsp;</a>&#957;&#903; VRS             : &#957;&#903; P<br><a NAME=\"25\">36                                n.               25&nbsp; &nbsp;</a>(&#948;&#8217;) add VRS  <br><a NAME=\"26\">38                                n.               26&nbsp; &nbsp;</a>[&#960;&#961;]&#8182;&#964;&#959;&#957;  VRS             : &#960;&#961;&#8182;&#964;&#959;&#957;  ed.pr.  <br><a NAME=\"27\">43                                n.               27&nbsp; &nbsp;</a>&#947;&#949;&#957;&#957;&#8053;&#963;&#945;&#963;&#952;&#945;&#953;&#903; VRS             : &#947;&#949;&#957;&#957;&#951;&#963;&#945;&#963;&#952;&#945;&#953;&#903; P<br></SPAN></b></td></FONT></tr></table></p>","author":"Mythographus Homericus","quotedauthor":"[Homerus, <i>Ilias</i> 7, 8, 9];Euphorion;Anticlides;Eratosthenes (R);Pherecydes Atheniensis (R).","genre":"commentary (selected lemmata)","type":"Homerica, mythology","contents":"mythological stories relating to Homeric lemmata from <i>Iliad</i> 7-9: <br>7.8: Arithous (1);<br>7.44: Helenus and Cassandra (2);<br>7.86: Hellespont (3);<br>8.479: gigantomachy (4);<br>9.447: Phoenix (5);<br>+ unidentified parts.<br>The second story is close to the scholia, but shorter in the end; the third is almost identical to the scholia, the fourth and fifth are quite different.","propernames":"<u>fr. 1 + fr. 2 col. I</u>: Pherekydês (R); Helenos (Q, R + 1 + R); Priamos (Q, R + 1); Hekabê (R); Kassandra (2); Apollôn; Thymbraios; Antikleidês; Hellêspontos (Q); Athamas; Aiolos (R); Thêbai [Thebes]; Inô (2R + 1); Kadmos (R); Learchos; Melikertês (R); Hêra; Nephelê (2); Hellê (R); Phrixos;<br><u>fr. 2 col. II + fr. 3</u>: Iapetos (Q, R); Kronos (Q, R + 1); Ouranos; Gê; Zeus; Euphoriôn; Hellas [Greece] (Q, R); Phoinix (R + 1); Amyntôr; Hippodameia; Phthia (R); Pêleus (R); Dolopia (R); Achilleus (R); Cheirôn (R); Eratosthenês (R).","mythological":"<u>fr. 1 + fr. 2 col. I</u>: Helenos (Q, R + 1 + R); Priamos (Q, R + 1); Hekabê (R); Kassandra (2); Apollôn; Thymbraios; Hellêspontos (Q); Athamas; Aiolos (R); Thêbai [Thebes]; Inô (2R + 1); Kadmos (R); Learchos; Melikertês (R); Hêra; Nephelê (2); Hellê (R); Phrixos;<br><u>fr. 2 col. II + fr. 3</u>: Iapetos (Q, R); Kronos (Q, R + 1); Ouranos; Gê; Zeus; Hellas [Greece] (Q, R); Phoinix (R + 1); Amyntôr; Hippodameia; Phthia (R); Pêleus (R); Dolopia (R); Achilleus (R); Cheirôn (R).","material":"papyrus","bookform":"roll","size":"8.3 x 11.7 (fr. 1 + fr. 2)7.2 x 13.4 (fr. 3)","script":"along the fibres","frontback":"blank","statepreservation":"(A) remains of 10 lines, broken off on both sides, which fit exactly into the gap in fr. 3, col. 2 of (B);<br>(B) three fragments with remains of two consecutive columns (intercolumnium: ca. 1.7 cm): col. 1 = fr. 1 + fr. 2, col. 1 + fr. 3, col. 1; col. 2 = fr. 2, col. 2 + fr. 3, col. 2. Of column 1, fr. 1 (broken off on both sides) has remains of 21 lines from the top, to which fr. 2, col. 1 adds the ends in l. 14-21, while fr. 3, col. 1, only shows a few letters; of column 2, only scanty remains of the beginnings of 5 lines appear on fr. 2, col. 2, while fr. 3, col. 2 has the starting words of 21 lines from the bottom of the column, with a large gap in l. 11-21, filled by (A).Since fr. 3, col. 2 comes shortly after fr. 2, col. 2, the column had at least 43 lines.","numberofcolumns":"02","columnwidth":"10.5 - 11 (R)","lettersperline":"38","lectionalsigns":"punctuation by blank space (fr. 2, col. 1, 2) and by high stop; lemmata in ekthesis; possible apostrophe (fr. 1, 1); trema (1); abbreviation (1); correction, probably by same hand (fr. 3, col. 2, 4); line-filler (1); iota adscript generally written.","hand":"medium-sized, informal, round, slightly flattened, upright, generally bilinear, regular, plain, written with care by a competent scribe, usually separating the letters, but with some ligatures and cursive elements; no decorations.","lastupdate":"2003/11/04 Marc Huys, Valerie Van Elst"}