{"id":406,"edition":"<i>P.Lugd.-Bat.</i> 13, 25 III (P. J. Sijpesteijn, 1965) = <i>P.Lugd.-Bat.</i> 25, 12 (C. Gallazzi, 1991)","inventory":"<a href=\"http://lhpc.arts.kuleuven.ac.be/collections/sample_coll.php?id=00180\">Leiden, Papyrologisch Instituut</a>, O. 1","ldab":"6667","trismegistos":"<a href=\"http://www.trismegistos.org/tm/detail.php?tm=65420\" target=\"_blank\">65420</a>","pack":"---","vanhaelst":"—","cribiore":"---","vrs":"---","asw":"---","gigante":"---","cpp":"0406","provenance":"Egypt, unknown","date":"AD 7 - AD 8","bibliography":"","plates":"<i>P.Lugd.-Bat.</i> 25, pl. V","url":"","greektext":"<p> base edition:<i>P.Lugd.-Bat.</i> 25, 12 (C. Gallazzi, 1991) <br> other edition: ed.pr. </p><a href=\"http://perswww.kuleuven.ac.be/~u0013314/unicode/CPP0406\">Greek text in Unicode</a><p><table cellspacing=22><tr><FONT size=+1><td align=left><font face=\"@arial unicode ms\"><FONT size=+1><p> <br>01 &nbsp; &nbsp; Leontios <br>02 &nbsp; &nbsp; Lesimaxos <br>03 &nbsp; &nbsp; Canqias <br>3a &nbsp; &nbsp; Agagios <br>04 &nbsp; &nbsp; Maurikios <br>05 &nbsp; &nbsp; Bubianos <br>06 &nbsp; &nbsp; Hlialhs O <br>07 &nbsp; &nbsp; Aqanasios <br>08 &nbsp; &nbsp; Korikonios <br>09 &nbsp; &nbsp; Aglaios </p></p></font></font></td> <td><b><span class=\"grec\"> <br>                &nbsp; &nbsp;                         -&nbsp;-&nbsp;-&nbsp;-&nbsp;-&nbsp;-&nbsp;-             &nbsp;&nbsp;&nbsp;&nbsp;&nbsp;&nbsp;<font size=\"-1\"></font>&nbsp;&nbsp;&nbsp;&nbsp;&nbsp;&nbsp;                        <br> 01                  &nbsp; &nbsp;                        <A STYLE=\"text-decoration: none\" HREF=\"#1\"><FONT color=\"#ff943d\">[&#923;&#949;&#8057;&#957;]&#964;&#953;&#959;&#962;<SUP>1</SUP></FONT></A> &nbsp; &nbsp;  &nbsp; &nbsp; [            <br> 02                  &nbsp; &nbsp;                        <A STYLE=\"text-decoration: none\" HREF=\"#2\"><FONT color=\"#ff943d\">[&#923;]&#949;&#803;&#963;&#8055;&#956;&#945;&#967;&#959;&#962;<SUP>2</SUP></FONT></A> &nbsp; &nbsp;  &nbsp; &nbsp; [            <br> 03                  &nbsp; &nbsp;                        <A STYLE=\"text-decoration: none\" HREF=\"#3\"><FONT color=\"#ff943d\">&#926;&#945;&#957;&#952;&#8055;&#945;&#962;<SUP>3</SUP></FONT></A> &nbsp; &nbsp;  &nbsp; &nbsp; [            <br>3a                &nbsp; &nbsp;                        <A STYLE=\"text-decoration: none\" HREF=\"#4\"><FONT color=\"#ff943d\">&#700; &#913;&#947;&#8049;&#947;&#953;&#959;&#962;<SUP>4</SUP></FONT></A> &nbsp; &nbsp;  &nbsp; &nbsp; [            <br> 04                  &nbsp; &nbsp;                        &#924;&#945;&#965;&#961;&#8055;&#954;&#953;&#959;&#962; &nbsp; &nbsp;  &nbsp; &nbsp; [            <br> 05                  &nbsp; &nbsp;                        &#914;&#965;&#946;&#953;&#945;&#957;&#8057;&#962; &nbsp; &nbsp;  &nbsp; &nbsp; [             <br> 06                  &nbsp; &nbsp;                        <A STYLE=\"text-decoration: none\" HREF=\"#5\"><FONT color=\"#ff943d\">&#701; &#919;&#955;&#953;&#8049;&#955;&#951;&#962;<SUP>5</SUP></FONT></A> &nbsp; &nbsp;  &nbsp; &nbsp; &#927;[            <br> 07                  &nbsp; &nbsp;                        &#700; &#913;&#952;&#945;&#957;&#8049;&#963;&#953;&#959;&#962;  &nbsp; &nbsp;  &nbsp; &nbsp; [             <br> 08                  &nbsp; &nbsp;                        &#922;&#959;&#961;&#954;&#8057;&#957;&#953;&#959;&#962; &nbsp; &nbsp;  &nbsp; &nbsp; [              <br> 09                  &nbsp; &nbsp;                        <A STYLE=\"text-decoration: none\" HREF=\"#6\"><FONT color=\"#ff943d\">&#8142; &#913;&#947;&#955;&#945;&#803;[&#953;&#959;&#962;<SUP>6</SUP></FONT></A>                                    <br><br><br><A NAME=\"1\"> 01                                  n.               01&nbsp; &nbsp;</A>[&#923;&#949;&#8057;&#957;]&#964;&#953;&#959;&#962; suppl Gallazzi             : &#8017;&#803;&#953;&#8057;&#962; ed.pr.  <br><A NAME=\"2\"> 02                                  n.               02&nbsp; &nbsp;</A>[&#923;]&#949;&#803;&#963;&#8055;&#956;&#945;&#967;&#959;&#962; Gallazzi             : &#931;&#803;&#8055;&#956;&#945;&#967;&#959;&#962; ed.pr.  <br><A NAME=\"3\"> 03                                  n.               03&nbsp; &nbsp;</A>&#926;&#945;&#957;&#952;&#8055;&#945;&#962; Gallazzi             : &#700; &#917;&#947;&#803;&#953;&#952;&#953;&#945;&#962; ed.pr.  <br><A NAME=\"4\">3a                                n.               04&nbsp; &nbsp;</A>&#700; &#913;&#947;&#8049;&#947;&#953;&#959;&#962; Gallazzi             : &#918;&#803;&#945;&#947;&#8049;&#963;&#803;&#953;&#959;&#962; ed.pr.  <br><A NAME=\"5\"> 06                                  n.               05&nbsp; &nbsp;</A>&#701; &#919;&#955;&#953;&#8049;&#955;&#951;&#962; Gallazzi             : &#922;&#803;&#955;&#953;&#8049;&#955;&#951;&#962; ed.pr.  <br><A NAME=\"6\"> 09                                  n.               06&nbsp; &nbsp;</A>&#8142; &#913;&#947;&#955;&#945;&#803;[&#953;&#959;&#962; suppl Gallazzi             :  &#700; &#913;&#947;&#955;&#945;[ ed.pr.  <br>\t</SPAN></b></td></FONT></tr></table></p>","author":"","quotedauthor":"","genre":"list of martyrs","type":"amulet","contents":"list of the martyrs of Sebaste (10 names preserved, and the initial letter of another one)","propernames":"Leontios; Lesimachos [Lysimachos]; Xanthias [Xanthios]; Agagios [Akakios]; Maurikios; Bybianos [Bibianos]; Êlialês [Hêlianos ?]; Athanasios; Korkonios [Gorgonios]; Aglaios","mythological":"","material":"ostracon","bookform":"sheet","size":"6 x 12.5","script":"","frontback":"blank","statepreservation":"incomplete ostracon (6 x 12.5 cm): the central section, the right-hand area and the top have been lost, so that only the beginnings of  9 lines arranged in a single column have been preserved. Left-hand margin reaches 0.6 cm at its maximum width, and lower margin is 1.5 cm deep.","numberofcolumns":"01","columnwidth":"05.5 (max. preserved)","lettersperline":"09 (max. preserved)","lectionalsigns":"correction by interlinear insertion. (Seemingly large) spaces separating items within the line.","hand":"small sloping capitals. Informal, but quite careful and writing separate letters (general sloping script?)","lastupdate":"2004/06/24 Alberto Nodar"}