{"id":525,"edition":"Wouters, The Chester Beatty codex AC 1499 p. 37-62, 115-147= Lowe, CLA Suppl. 1683","inventory":"Dublin, Chester Beatty Library Ac. 1499","ldab":"3030","trismegistos":"<a href=\"http://www.trismegistos.org/tm/detail.php?tm=61873\" target=\"_blank\">61873</a>","pack":"","vanhaelst":"0511","cribiore":"","vrs":"","asw":"","gigante":"","cpp":"0525","provenance":"Egypt, unknown","date":"AD 5","bibliography":"","plates":"","url":"","greektext":"","author":"","quotedauthor":"","genre":"","type":"","contents":"glossary on 02 Corinthians, Galatians, Ephesians; conjugation poieo, boao, chrusoo, pleko + alphabet","propernames":"","mythological":"","material":"papyrus","bookform":"","size":"","script":"","frontback":"","statepreservation":"","numberofcolumns":"","columnwidth":"","lettersperline":"","lectionalsigns":"","hand":"","lastupdate":""}